Metadata-Version: 1.0
Name: aclib
Version: 0.1.2
Summary: The Alphacruncher python library
Home-page: https://github.com/datahub-ac/python-connector
Author: Alphacruncher
Author-email: support@alphacruncher.com
License: MIT
Platform: UNKNOWN
